{
    "chapitre": "Algèbre",
    "flc": [
        {
            "corrige": "Caractérisation endo symétrique.png",
            "enonce": "Caractérisation endo symétrique",
            "importance": 1
        },
        {
            "corrige": "Caractérisation isométrie .png",
            "enonce": "Caractérisation isométrie ",
            "importance": 1
        },
        {
            "corrige": "Caractérisation matrices orthogonales.png",
            "enonce": "Caractérisation matrices orthogonales",
            "importance": 1
        },
        {
            "corrige": "Def endo orthogonal.png",
            "enonce": "Def endo orthogonal",
            "importance": 1
        },
        {
            "corrige": "Def endo symétrique.png",
            "enonce": "Def endo symétrique",
            "importance": 1
        },
        {
            "corrige": "Def famille orthonormale.png",
            "enonce": "Def famille orthonormale",
            "importance": 1
        },
        {
            "corrige": "Def isométrie direct_indirecte.png",
            "enonce": "Def isométrie direct_indirecte",
            "importance": 1
        },
        {
            "corrige": "Def isométrie.png",
            "enonce": "Def isométrie",
            "importance": 1
        },
        {
            "corrige": "Def l'orthogonal de A.png",
            "enonce": "Def l'orthogonal de A",
            "importance": 1
        },
        {
            "corrige": "Def norme produit scalaire.png",
            "enonce": "Def norme produit scalaire",
            "importance": 1
        },
        {
            "corrige": "Def orientation des bases.png",
            "enonce": "Def orientation des bases",
            "importance": 1
        },
        {
            "corrige": "Def produit mixte.png",
            "enonce": "Def produit mixte",
            "importance": 1
        },
        {
            "corrige": "Def produit scalaire.png",
            "enonce": "Def produit scalaire",
            "importance": 1
        },
        {
            "corrige": "Def projection orthogonale sur F.png",
            "enonce": "Def projection orthogonale sur F",
            "importance": 1
        },
        {
            "corrige": "Def réflexion.png",
            "enonce": "Def réflexion",
            "importance": 1
        },
        {
            "corrige": "Def symétrie orthogonale.png",
            "enonce": "Def symétrie orthogonale",
            "importance": 1
        },
        {
            "corrige": "Def vecteurs orthogonaux.png",
            "enonce": "Def vecteurs orthogonaux",
            "importance": 1
        },
        {
            "corrige": "Décomposition d'un EV avec un SEV.png",
            "enonce": "Décomposition d'un EV avec un SEV",
            "importance": 1
        },
        {
            "corrige": "Déterminant famille vecteur dans une autre base.png",
            "enonce": "Déterminant famille vecteur dans une autre base",
            "importance": 1
        },
        {
            "corrige": "Déterminant image d'une base.png",
            "enonce": "Déterminant image d'une base",
            "importance": 1
        },
        {
            "corrige": "Déterminant matrice orthogonale.png",
            "enonce": "Déterminant matrice orthogonale",
            "importance": 1
        },
        {
            "corrige": "Déterminant_Spectre pour f orthogonale.png",
            "enonce": "Déterminant_Spectre pour f orthogonale",
            "importance": 1
        },
        {
            "corrige": "Formule Bessel-Parseval en dim finie.png",
            "enonce": "Formule Bessel-Parseval en dim finie",
            "importance": 1
        },
        {
            "corrige": "Formule produit scalaire avec angle.png",
            "enonce": "Formule produit scalaire avec angle",
            "importance": 1
        },
        {
            "corrige": "Formule projection orthogonale.png",
            "enonce": "Formule projection orthogonale",
            "importance": 1
        },
        {
            "corrige": "Formule symétrie ortho en fonction projection.png",
            "enonce": "Formule symétrie ortho en fonction projection",
            "importance": 1
        },
        {
            "corrige": "Gram-Schmidt.png",
            "enonce": "Gram-Schmidt",
            "importance": 1
        },
        {
            "corrige": "Identité remarquable_parallélogramme_polarisation.png",
            "enonce": "Identité remarquable_parallélogramme_polarisation",
            "importance": 1
        },
        {
            "corrige": "Inégalité de Bessel.png",
            "enonce": "Inégalité de Bessel",
            "importance": 1
        },
        {
            "corrige": "Inégalité de Cauchy-Schwartz.png",
            "enonce": "Inégalité de Cauchy-Schwartz",
            "importance": 1
        },
        {
            "corrige": "Lemme technique endo_mat symétrique.png",
            "enonce": "Lemme technique endo_mat symétrique",
            "importance": 1
        },
        {
            "corrige": "Matrice de passage entre deux BON.png",
            "enonce": "Matrice de passage entre deux BON",
            "importance": 1
        },
        {
            "corrige": "Matrice isométire indirecte.png",
            "enonce": "Matrice isométire indirecte",
            "importance": 1
        },
        {
            "corrige": "Matrice isométrie directe.png",
            "enonce": "Matrice isométrie directe",
            "importance": 1
        },
        {
            "corrige": "Matrice_trace d'une isométrie direct_indirecte dans l'espace.png",
            "enonce": "Matrice_trace d'une isométrie direct_indirecte dans l'espace",
            "importance": 1
        },
        {
            "corrige": "Produit scalaire matrice.png",
            "enonce": "Produit scalaire matrice",
            "importance": 1
        },
        {
            "corrige": "Prop sous espaces 2 à 2 orthogonaux.png",
            "enonce": "Prop sous espaces 2 à 2 orthogonaux",
            "importance": 1
        },
        {
            "corrige": "Propriété d'une famille orthogonale non nuls_orthonormale.png",
            "enonce": "Propriété d'une famille orthogonale non nuls_orthonormale",
            "importance": 1
        },
        {
            "corrige": "Propriétés matrices orthogonales.png",
            "enonce": "Propriétés matrices orthogonales",
            "importance": 1
        },
        {
            "corrige": "Theorème de la BON incomplète.png",
            "enonce": "Theorème de la BON incomplète",
            "importance": 1
        },
        {
            "corrige": "Théorème de Riesz.png",
            "enonce": "Théorème de Riesz",
            "importance": 1
        },
        {
            "corrige": "Théorème spectral + version matrice.png",
            "enonce": "Théorème spectral + version matrice",
            "importance": 1
        },
        {
            "corrige": "Théorème sur la projection orthogonale.png",
            "enonce": "Théorème sur la projection orthogonale",
            "importance": 1
        },
        {
            "corrige": "Théorème_réciproque Pythagore.png",
            "enonce": "Théorème_réciproque Pythagore",
            "importance": 1
        }
    ],
    "sous-chapitre": "04 Algèbre bilinéaire"
}